my_mips.srcs/sources_1/new/pc_calculator.v
module pc_calculator(
    input [31:0] pc,
    input [25:0] jump_addr,
    input [31:0] branch_addr,
    input branch,
    input jump,
    input zero,
    input [31:0] reg_data1,
    input [5:0] funct,      // 添加: 用于判断是否为JR指令
    input [5:0] opcode,     // 添加: 用于指令类型判断
    output reg [31:0] next_pc
);

    wire [31:0] branch_offset = branch_addr << 2;
    wire [31:0] pc_plus_4 = pc + 32'd4;
    wire [31:0] branch_target = pc_plus_4 + branch_offset;
    wire [31:0] jump_target = {pc_plus_4[31:28], jump_addr, 2'b00};
    wire is_jr = (opcode == 6'b000000 && funct == 6'b001000); // 判断是否为JR指令
    
    always @(*) begin
        if (jump) begin
            if (is_jr) begin
                next_pc = reg_data1; // JR指令: 跳转到寄存器中的地址
            end
            else begin
                next_pc = jump_target; // J/JAL指令: 跳转到立即数指定的地址
            end
        end
        else if (branch && zero) begin // BEQ
            next_pc = branch_target;
        end
        else if (branch && !zero) begin // BNE
            next_pc = branch_target;
        end
        else if (branch && $signed(reg_data1) < 0) begin // BLTZ
            next_pc = branch_target;
        end
        else if (branch && $signed(reg_data1) >= 0) begin // BGEZ
            next_pc = branch_target;
        end
        else begin
            next_pc = pc_plus_4;
        end
    end
endmodule

my_mips.srcs/sources_1/new/data_memory.v
module data_memory(
    input clk,
    input reset,
    input [5:0] addr,
    input [31:0] write_data,
    input write_en,
    output reg [31:0] read_data
);

    reg [31:0] mem [0:63];
    integer i;
    
    // 初始化数据存储器
    initial begin
        for (i = 0; i < 64; i = i + 1) begin
            mem[i] = i * 4; // 地址值乘以4
        end
    end
    
    always @(negedge clk) begin
        if (reset) begin
            for (i = 0; i < 64; i = i + 1) begin
                mem[i] <= i * 4;
            end
        end
        else if (write_en) begin
            mem[addr] <= write_data;
        end
    end
    
    always @(*) begin
        read_data = mem[addr];
    end
endmodule

my_mips.srcs/sources_1/new/extend.v
module sign_extend(
    input [15:0] in,
    output reg [31:0] out
);

    always @(*) begin
        out = {{16{in[15]}}, in};
    end
endmodule

module zero_extend(
    input [15:0] in,
    output reg [31:0] out
);

    always @(*) begin
        out = {16'b0, in};
    end
endmodule

my_mips.srcs/sources_1/new/alu.v
module alu(
    input [31:0] a,
    input [31:0] b,
    input [3:0] control,
    output reg [31:0] result,
    output zero
);

    assign zero = (result == 32'b0);
    
    always @(*) begin
        case (control)
            4'b0000: result = a & b;    // AND
            4'b0001: result = a | b;    // OR
            4'b0010: result = a + b;    // ADD
            4'b0110: result = a - b;    // SUB
            4'b0111: result = (a < b) ? 32'd1 : 32'd0; // SLT
            4'b1100: result = ~(a | b); // NOR
            default: result = 32'b0;
        endcase
    end
endmodule

my_mips.srcs/sources_1/new/control_unit.v
module control_unit(
    input [5:0] opcode,
    input [5:0] funct,
    output reg [1:0] reg_dst,
    output reg alu_src,
    output reg [1:0] mem_to_reg,
    output reg reg_write,
    output reg mem_write,
    output reg [3:0] alu_control,
    output reg branch,
    output reg jump
);

    always @(*) begin
        case (opcode)
            6'b000000: begin // R-type
                reg_dst = 2'b01;
                alu_src = 1'b0;
                mem_to_reg = 2'b00;
                reg_write = 1'b1;
                mem_write = 1'b0;
                branch = 1'b0;
                jump = 1'b0;
                
                case (funct)
                    6'b100000: alu_control = 4'b0010; // ADD
                    6'b100010: alu_control = 4'b0110; // SUB
                    6'b100100: alu_control = 4'b0000; // AND
                    6'b100101: alu_control = 4'b0001; // OR
                    6'b101010: alu_control = 4'b0111; // SLT
                    6'b001000: begin alu_control = 4'b0000; jump = 1'b1; reg_write = 1'b0; end // JR
                    default: alu_control = 4'b0000;
                endcase
            end
            
            6'b100011: begin // LW
                reg_dst = 2'b00;
                alu_src = 1'b1;
                mem_to_reg = 2'b01;
                reg_write = 1'b1;
                mem_write = 1'b0;
                alu_control = 4'b0010;
                branch = 1'b0;
                jump = 1'b0;
            end
            
            6'b101011: begin // SW
                reg_dst = 2'b00;
                alu_src = 1'b1;
                mem_to_reg = 2'b00;
                reg_write = 1'b0;
                mem_write = 1'b1;
                alu_control = 4'b0010;
                branch = 1'b0;
                jump = 1'b0;
            end
            
            6'b000100: begin // BEQ
                reg_dst = 2'b00;
                alu_src = 1'b0;
                mem_to_reg = 2'b00;
                reg_write = 1'b0;
                mem_write = 1'b0;
                alu_control = 4'b0110;
                branch = 1'b1;
                jump = 1'b0;
            end
            
            6'b000101: begin // BNE
                reg_dst = 2'b00;
                alu_src = 1'b0;
                mem_to_reg = 2'b00;
                reg_write = 1'b0;
                mem_write = 1'b0;
                alu_control = 4'b0110;
                branch = 1'b1;
                jump = 1'b0;
            end
            
            6'b000010: begin // J
                reg_dst = 2'b00;
                alu_src = 1'b0;
                mem_to_reg = 2'b00;
                reg_write = 1'b0;
                mem_write = 1'b0;
                alu_control = 4'b0000;
                branch = 1'b0;
                jump = 1'b1;
            end
            
            6'b000011: begin // JAL
                reg_dst = 2'b10;
                alu_src = 1'b0;
                mem_to_reg = 2'b10;
                reg_write = 1'b1;
                mem_write = 1'b0;
                alu_control = 4'b0000;
                branch = 1'b0;
                jump = 1'b1;
            end
            
            6'b001000: begin // ADDI
                reg_dst = 2'b00;
                alu_src = 1'b1;
                mem_to_reg = 2'b00;
                reg_write = 1'b1;
                mem_write = 1'b0;
                alu_control = 4'b0010;
                branch = 1'b0;
                jump = 1'b0;
            end
            
            6'b001101: begin // ORI
                reg_dst = 2'b00;
                alu_src = 1'b1;
                mem_to_reg = 2'b00;
                reg_write = 1'b1;
                mem_write = 1'b0;
                alu_control = 4'b0001;
                branch = 1'b0;
                jump = 1'b0;
            end
            
            6'b100000: begin // LB
                reg_dst = 2'b00;
                alu_src = 1'b1;
                mem_to_reg = 2'b01;
                reg_write = 1'b1;
                mem_write = 1'b0;
                alu_control = 4'b0010;
                branch = 1'b0;
                jump = 1'b0;
            end
            
            6'b100100: begin // LBU
                reg_dst = 2'b00;
                alu_src = 1'b1;
                mem_to_reg = 2'b01;
                reg_write = 1'b1;
                mem_write = 1'b0;
                alu_control = 4'b0010;
                branch = 1'b0;
                jump = 1'b0;
            end
            
            6'b100001: begin // LH
                reg_dst = 2'b00;
                alu_src = 1'b1;
                mem_to_reg = 2'b01;
                reg_write = 1'b1;
                mem_write = 1'b0;
                alu_control = 4'b0010;
                branch = 1'b0;
                jump = 1'b0;
            end
            
            6'b100101: begin // LHU
                reg_dst = 2'b00;
                alu_src = 1'b1;
                mem_to_reg = 2'b01;
                reg_write = 1'b1;
                mem_write = 1'b0;
                alu_control = 4'b0010;
                branch = 1'b0;
                jump = 1'b0;
            end
            
            6'b000001: begin // BLTZ/BGEZ
                reg_dst = 2'b00;
                alu_src = 1'b0;
                mem_to_reg = 2'b00;
                reg_write = 1'b0;
                mem_write = 1'b0;
                alu_control = 4'b0111;
                branch = 1'b1;
                jump = 1'b0;
            end
            
            default: begin
                reg_dst = 2'b00;
                alu_src = 1'b0;
                mem_to_reg = 2'b00;
                reg_write = 1'b0;
                mem_write = 1'b0;
                alu_control = 4'b0000;
                branch = 1'b0;
                jump = 1'b0;
            end
        endcase
    end
endmodule

my_mips.srcs/sources_1/new/reg_file.v
module reg_file(
    input clk,
    input reset,
    input [4:0] read_reg1,
    input [4:0] read_reg2,
    input [4:0] write_reg,
    input [31:0] write_data,
    input write_en,
    output reg [31:0] read_data1,
    output reg [31:0] read_data2
);

    reg [31:0] registers [0:31];
    integer i;
    
    // 初始化寄存器文件
    initial begin
        for (i = 0; i < 32; i = i + 1) begin
            registers[i] = i * 4;
        end
    end
    
    always @(negedge clk or posedge reset) begin
        if (reset) begin
            for (i = 0; i < 32; i = i + 1) begin
                registers[i] <= i * 4;
            end
        end
        else if (write_en && write_reg != 0) begin
            registers[write_reg] <= write_data;
        end
    end
    
    always @(*) begin
        read_data1 = (read_reg1 == 0) ? 32'b0 : registers[read_reg1];
        read_data2 = (read_reg2 == 0) ? 32'b0 : registers[read_reg2];
    end
endmodule

my_mips.srcs/sources_1/new/instruction_memory.v
module instruction_memory(
    input clk,
    input [5:0] addr,
    output reg [31:0] instruction
);

    reg [31:0] mem [0:63];
    

    initial begin
        // 基础功能
//        mem[0] = 32'h00000000;
//        mem[1] = 32'h00432020; // add $4,$2,$3
//        mem[2] = 32'h8c440004; // lw $4,4($2)
//        mem[3] = 32'hac450008; // sw $5,8($2)
//        mem[4] = 32'h00831022; // sub $2,$4,$3
//        mem[5] = 32'h00831025; // or $2,$4,$3
//        mem[6] = 32'h00831024; // and $2,$4,$3
//        mem[7] = 32'h0083102a; // slt $2,$4,$3
//        mem[8] = 32'h10630001; // beq $3,$3,equ (PC+1+1)
//        mem[9] = 32'h8c620000; // lw $2,0($3)
////        equ:
//        mem[10] = 32'h10640001; // beq $3,$4,exit (PC+1+1)
//        mem[11] = 32'hac620000; // sw $2,0($3)
////        exit:
//        mem[12] = 32'h08000000; // j main (PC = 0)
        
        //jal jr测试
        mem[0] = 32'h00000000;        // NOP
        mem[1] = 32'h0c000005;        // jal 20 (20为函数slt $2,$4,$3)
        mem[2] = 32'h00432020;        // add $4,$2,$3
        mem[3] = 32'h08000000;        // j 0
        mem[4] = 32'h00000000;        // NOP
        // 子函数
        mem[5] = 32'h00000000;        // NOP原因：指令存储器的取指时序与PC更新时序之间的不匹配
        mem[6] = 32'h0083102a;        // slt $2,$4,$3
        mem[7] = 32'h03e00008;        // jr $31 (return 主函数)
        
//////////扩展
//        mem[13] = 32'h2062000a; // addi $2,$3,10
//        mem[14] = 32'h3462000f; // ori $2,$3,0xf
//        mem[15] = 32'h80420000; // lb $2,0($2)
//        mem[16] = 32'h90420000; // lbu $2,0($2)
//        mem[17] = 32'h84420000; // lh $2,0($2)
//        mem[18] = 32'h94420000; // lhu $2,0($2)
//        mem[19] = 32'h14640001; // bne $3,$4,exit (PC+1+1)
//        mem[20] = 32'h04600001; // bltz $3,exit (PC+1+1)
//        mem[21] = 32'h04610001; // bgez $3,exit (PC+1+1)
//        mem[22] = 32'h0c000000; // jal 0
//        mem[23] = 32'h03e00008; // jr $31
    end
    
    always @(posedge clk) begin
        instruction <= mem[addr];
    end
endmodule

my_mips.srcs/sources_1/new/mips_cpu.v
module mips_cpu(
    input clk,
    input reset
);

    // 内部信号定义
    wire [31:0] pc, next_pc, instruction;
    wire [31:0] reg_data1, reg_data2, alu_result, mem_read_data;
    wire [31:0] sign_extend, zero_extend;
    wire [4:0] write_reg;
    wire [31:0] reg_write_data;
    wire reg_write_en, mem_write_en;
    wire [3:0] alu_control;
    wire [1:0] reg_dst, mem_to_reg;
    wire alu_src, branch, jump, zero;
    
    // 时钟边沿控制
    reg clk_rise = 0, clk_fall = 0;  // 添加初始值
    always @(posedge clk) clk_rise <= ~clk_rise;
    always @(negedge clk) clk_fall <= ~clk_fall;
    
    // PC寄存器 (下降沿更新)
    reg [31:0] pc_reg;
    always @(negedge clk or posedge reset) begin
        if (reset) pc_reg <= 32'b0;
        else pc_reg <= next_pc;
    end
    assign pc = pc_reg;
    
    // 指令存储器 (上升沿读取)
    instruction_memory imem(
        .clk(clk),
        .addr(pc[7:2]),
        .instruction(instruction)
    );
    
    // 寄存器文件
    reg_file registers(
        .clk(clk_fall),
        .reset(reset),
        .read_reg1(instruction[25:21]),
        .read_reg2(instruction[20:16]),
        .write_reg(write_reg),
        .write_data(reg_write_data),
        .write_en(reg_write_en),
        .read_data1(reg_data1),
        .read_data2(reg_data2)
    );
    
    // 控制单元
    control_unit control(
        .opcode(instruction[31:26]),
        .funct(instruction[5:0]),
        .reg_dst(reg_dst),
        .alu_src(alu_src),
        .mem_to_reg(mem_to_reg),
        .reg_write(reg_write_en),
        .mem_write(mem_write_en),
        .alu_control(alu_control),
        .branch(branch),
        .jump(jump)
    );
    
    // ALU
    alu main_alu(
        .a(reg_data1),
        .b(alu_src ? sign_extend : reg_data2),
        .control(alu_control),
        .result(alu_result),
        .zero(zero)
    );
    
    // 符号扩展
    sign_extend sign_ext(
        .in(instruction[15:0]),
        .out(sign_extend)
    );
    
    // 零扩展
    zero_extend zero_ext(
        .in(instruction[15:0]),
        .out(zero_extend)
    );
    
    // 数据存储器 (下降沿写入)
    data_memory dmem(
        .clk(clk_fall),
        .reset(reset),
        .addr(alu_result[7:2]),
        .write_data(reg_data2),
        .write_en(mem_write_en),
        .read_data(mem_read_data)
    );
    
    // 下一条PC计算
    pc_calculator pc_calc(
        .pc(pc),
        .jump_addr(instruction[25:0]),
        .branch_addr(sign_extend),
        .branch(branch),
        .jump(jump),
        .zero(zero),
        .reg_data1(reg_data1),
        .funct(instruction[5:0]),    // 添加: 传递funct字段
        .opcode(instruction[31:26]), // 添加: 传递opcode字段
        .next_pc(next_pc)
    );
    
    // 写回寄存器选择
    assign write_reg = (reg_dst == 2'b00) ? instruction[20:16] :
                      (reg_dst == 2'b01) ? instruction[15:11] :
                      5'b11111; // 用于JAL指令
    
    // 写回数据选择
    assign reg_write_data = (mem_to_reg == 2'b00) ? alu_result :
                           (mem_to_reg == 2'b01) ? mem_read_data :
                           (mem_to_reg == 2'b10) ? {pc + 32'd4} :
                           zero_extend; // 用于LUI指令
endmodule

my_mips.srcs/sim_1/new/testbench.v
`timescale 1ns/1ps

module mips_cpu_tb;

    reg clk;
    reg reset;
    
    // 实例化CPU
    mips_cpu cpu(.clk(clk), .reset(reset));
    
    // 时钟生成
    initial begin
        clk = 0;
        forever #5 clk = ~clk;
    end

    initial begin
        $dumpfile("cpu_trace.vcd");
        $dumpvars(0, mips_cpu_tb);
        
        // 基本监视信号
        $monitor("Time=%0t: PC=%h, Inst=%h", $time, cpu.pc, cpu.instruction);
    end
    
    // 初始化和reset配置
    initial begin
        // 应用reset
        reset = 1;
        #20;  // 保持reset一段时间
        reset = 0;
        
        // 运行足够的仿真时间
        #500;
        $finish;
    end
    
    // 保留R型指令解码函数供可能的调试使用
    function [64:0] get_r_type_name;
        input [5:0] funct;
        begin
            case (funct)
                6'b100000: get_r_type_name = "ADD";
                6'b100010: get_r_type_name = "SUB";
                6'b100100: get_r_type_name = "AND";
                6'b100101: get_r_type_name = "OR";
                6'b101010: get_r_type_name = "SLT";
                6'b001000: get_r_type_name = "JR";
                default: get_r_type_name = "Unknown";
            endcase
        end
    endfunction
endmodule

my_mips.sim/sim_1/behav/xsim/cpu_trace.vcd
$date
   Thu May  8 16:23:23 2025
$end
$version
  2018.3
$end
$timescale
  1ps
$end
$scope module mips_cpu_tb $end
$var reg 1 ! clk $end
$var reg 1 " reset $end
$scope module cpu $end
$var wire 1 # clk $end
$var wire 1 $ reset $end
$var wire 32 % pc [31:0] $end
$var wire 32 & next_pc [31:0] $end
$var wire 32 ' instruction [31:0] $end
$var wire 32 ( reg_data1 [31:0] $end
$var wire 32 ) reg_data2 [31:0] $end
$var wire 32 * alu_result [31:0] $end
$var wire 32 + mem_read_data [31:0] $end
$var wire 32 , sign_extend [31:0] $end
$var wire 32 - zero_extend [31:0] $end
$var wire 5 . write_reg [4:0] $end
$var wire 32 / reg_write_data [31:0] $end
$var wire 1 0 reg_write_en $end
$var wire 1 1 mem_write_en $end
$var wire 4 2 alu_control [3:0] $end
$var wire 2 3 reg_dst [1:0] $end
$var wire 2 4 mem_to_reg [1:0] $end
$var wire 1 5 alu_src $end
$var wire 1 6 branch $end
$var wire 1 7 jump $end
$var wire 1 8 zero $end
$var reg 1 9 clk_rise $end
$var reg 1 : clk_fall $end
$var reg 32 ; pc_reg [31:0] $end
$scope module imem $end
$var wire 1 # clk $end
$var wire 6 < addr [5:0] $end
$var reg 32 = instruction [31:0] $end
$upscope $end
$scope module registers $end
$var wire 1 > clk $end
$var wire 1 $ reset $end
$var wire 5 ? read_reg1 [4:0] $end
$var wire 5 @ read_reg2 [4:0] $end
$var wire 5 . write_reg [4:0] $end
$var wire 32 / write_data [31:0] $end
$var wire 1 0 write_en $end
$var reg 32 A read_data1 [31:0] $end
$var reg 32 B read_data2 [31:0] $end
$var integer 32 C i $end
$upscope $end
$scope module control $end
$var wire 6 D opcode [5:0] $end
$var wire 6 E funct [5:0] $end
$var reg 2 F reg_dst [1:0] $end
$var reg 1 G alu_src $end
$var reg 2 H mem_to_reg [1:0] $end
$var reg 1 I reg_write $end
$var reg 1 J mem_write $end
$var reg 4 K alu_control [3:0] $end
$var reg 1 L branch $end
$var reg 1 M jump $end
$upscope $end
$scope module main_alu $end
$var wire 32 ( a [31:0] $end
$var wire 32 N b [31:0] $end
$var wire 4 2 control [3:0] $end
$var reg 32 O result [31:0] $end
$var wire 1 8 zero $end
$upscope $end
$scope module sign_ext $end
$var wire 16 P in [15:0] $end
$var reg 32 Q out [31:0] $end
$upscope $end
$scope module zero_ext $end
$var wire 16 P in [15:0] $end
$var reg 32 R out [31:0] $end
$upscope $end
$scope module dmem $end
$var wire 1 S clk $end
$var wire 1 $ reset $end
$var wire 6 T addr [5:0] $end
$var wire 32 ) write_data [31:0] $end
$var wire 1 1 write_en $end
$var reg 32 U read_data [31:0] $end
$var integer 32 V i $end
$upscope $end
$scope module pc_calc $end
$var wire 32 % pc [31:0] $end
$var wire 26 W jump_addr [25:0] $end
$var wire 32 , branch_addr [31:0] $end
$var wire 1 6 branch $end
$var wire 1 7 jump $end
$var wire 1 8 zero $end
$var wire 32 ( reg_data1 [31:0] $end
$var wire 6 E funct [5:0] $end
$var wire 6 D opcode [5:0] $end
$var reg 32 X next_pc [31:0] $end
$var wire 32 Y branch_offset [31:0] $end
$var wire 32 Z pc_plus_4 [31:0] $end
$var wire 32 [ branch_target [31:0] $end
$var wire 32 \ jump_target [31:0] $end
$var wire 1 ] is_jr $end
$upscope $end
$upscope $end
$upscope $end
$enddefinitions $end
#0
$dumpvars
0!
1"
0#
1$
b0 %
b100 &
bx '
bx (
bx )
bx *
bx +
bx ,
bx -
bx .
bx /
x0
x1
bx 2
bx 3
bx 4
x5
x6
x7
x8
09
1:
b0 ;
b0 <
bx =
1>
bx ?
bx @
bx A
bx B
b100000 C
bx D
bx E
bx F
xG
bx H
xI
xJ
bx K
xL
xM
bx N
bx O
bx P
bx Q
bx R
1S
bx T
bx U
b1000000 V
bx W
b100 X
bx00 Y
b100 Z
bx [
b0xxxxxxxxxxxxxxxxxxxxxxxxxx00 \
x]
$end
#5000
1!
1#
b0 '
b0 (
b0 )
b0 *
b0 +
b0 ,
b0 -
b0 .
b0 /
10
01
b0 2
b1 3
b0 4
05
06
07
18
19
b0 =
b0 ?
b0 @
b0 A
b0 B
b0 D
b0 E
b1 F
0G
b0 H
1I
0J
b0 K
0L
0M
b0 N
b0 O
b0 P
b0 Q
b0 R
b0 T
b0 U
b0 W
b100 X
b0 Y
b100 [
b0 \
0]
#10000
0!
0#
0:
0>
b100000 C
0S
b1000000 V
#15000
1!
1#
09
#20000
0!
0"
0#
0$
b100 %
b1000 &
1:
b100 ;
b1 <
1>
1S
b1000 X
b1000 Z
b1000 [
#25000
1!
1#
b10100 &
b1100000000000000000000000101 '
b101 ,
b101 -
b11111 .
b1000 /
b10 3
b10 4
17
19
b1100000000000000000000000101 =
b0 ?
b0 @
b11 D
b101 E
b10 F
0G
b10 H
1I
0J
b0 K
0L
1M
b0 N
b101 P
b101 Q
b101 R
b101 W
b10100 X
b10100 Y
b11100 [
b10100 \
0]
#30000
0!
0#
b10100 %
b11000 /
0:
b10100 ;
b101 <
0>
b0 A
b0 B
0S
b10100 X
b11000 Z
b101100 [
#35000
1!
1#
b11000 &
b0 '
b0 ,
b0 -
b0 .
b0 /
b1 3
b0 4
07
09
b0 =
b0 ?
b0 @
b0 D
b0 E
b1 F
0G
b0 H
1I
0J
b0 K
0L
0M
b0 N
b0 P
b0 Q
b0 R
b0 W
b11000 X
b0 Y
b11000 [
b0 \
0]
#40000
0!
0#
b11000 %
b11100 &
1:
b11000 ;
b110 <
1>
1S
b11100 X
b11100 Z
b11100 [
#45000
1!
1#
b100000110001000000101010 '
b10000 (
b1100 )
b1000000101010 ,
b1000000101010 -
b10 .
b111 2
19
b100000110001000000101010 =
b100 ?
b11 @
b10000 A
b1100 B
b0 D
b101010 E
b1 F
0G
b0 H
1I
0J
b111 K
0L
0M
b1100 N
b0 O
b1000000101010 P
b1000000101010 Q
b1000000101010 R
b100000110001000000101010 W
b11100 X
b100000010101000 Y
b100000011000100 [
b10000011000100000010101000 \
0]
#50000
0!
0#
b11100 %
b100000 &
0:
b11100 ;
b111 <
0>
b10000 A
b1100 B
0S
b100000 X
b100000 Z
b100000011001000 [
#55000
1!
1#
b1000 &
b11111000000000000000001000 '
b1000 (
b0 )
b1000 ,
b1000 -
b0 .
00
b0 2
17
09
b11111000000000000000001000 =
b11111 ?
b0 @
b1000 A
b0 B
b0 D
b1000 E
b1 F
0G
b0 H
0I
0J
b0 K
0L
1M
b0 N
b0 O
b1000 P
b1000 Q
b1000 R
b11111000000000000000001000 W
b1000 X
b100000 Y
b1000000 [
b1111100000000000000000100000 \
1]
#60000
0!
0#
b1000 %
1:
b1000 ;
b10 <
1>
1S
b1000 X
b1100 Z
b101100 [
#65000
1!
1#
b1100 &
b10000110010000000100000 '
b0 (
b1100 )
b1100 *
b1100 +
b10000000100000 ,
b10000000100000 -
b100 .
b1100 /
10
b10 2
07
08
19
b10000110010000000100000 =
b10 ?
b11 @
b0 A
b1100 B
b0 D
b100000 E
b1 F
0G
b0 H
1I
0J
b10 K
0L
0M
b1100 N
b1100 O
b10000000100000 P
b10000000100000 Q
b10000000100000 R
b11 T
b1100 U
b10000110010000000100000 W
b1100 X
b1000000010000000 Y
b1000000010001100 [
b1000011001000000010000000 \
0]
#70000
0!
0#
b1100 %
b10000 &
0:
b1100 ;
b11 <
0>
b0 A
b1100 B
0S
b10000 X
b10000 Z
b1000000010010000 [
#75000
1!
1#
b0 &
b1000000000000000000000000000 '
b0 )
b0 *
b0 +
b0 ,
b0 -
b0 .
b0 /
00
b0 2
b0 3
17
18
09
b1000000000000000000000000000 =
b0 ?
b0 @
b0 A
b0 B
b10 D
b0 E
b0 F
0G
b0 H
0I
0J
b0 K
0L
1M
b0 N
b0 O
b0 P
b0 Q
b0 R
b0 T
b0 U
b0 W
b0 X
b0 Y
b10000 [
b0 \
0]
#80000
0!
0#
b0 %
1:
b0 ;
b0 <
1>
1S
b0 X
b100 Z
b100 [
#85000
1!
1#
b100 &
b0 '
10
b1 3
07
19
b0 =
b0 ?
b0 @
b0 D
b0 E
b1 F
0G
b0 H
1I
0J
b0 K
0L
0M
b0 P
b0 W
b100 X
0]
#90000
0!
0#
b100 %
b1000 &
0:
b100 ;
b1 <
0>
0S
b1000 X
b1000 Z
b1000 [
#95000
1!
1#
b10100 &
b1100000000000000000000000101 '
b101 ,
b101 -
b11111 .
b1000 /
b10 3
b10 4
17
09
b1100000000000000000000000101 =
b0 ?
b0 @
b11 D
b101 E
b10 F
0G
b10 H
1I
0J
b0 K
0L
1M
b0 N
b101 P
b101 Q
b101 R
b101 W
b10100 X
b10100 Y
b11100 [
b10100 \
0]
#100000
0!
0#
b10100 %
b11000 /
1:
b10100 ;
b101 <
1>
1S
b10100 X
b11000 Z
b101100 [
#105000
1!
1#
b11000 &
b0 '
b0 ,
b0 -
b0 .
b0 /
b1 3
b0 4
07
19
b0 =
b0 ?
b0 @
b0 D
b0 E
b1 F
0G
b0 H
1I
0J
b0 K
0L
0M
b0 N
b0 P
b0 Q
b0 R
b0 W
b11000 X
b0 Y
b11000 [
b0 \
0]
#110000
0!
0#
b11000 %
b11100 &
0:
b11000 ;
b110 <
0>
0S
b11100 X
b11100 Z
b11100 [
#115000
1!
1#
b100000110001000000101010 '
b1100 (
b1100 )
b1000000101010 ,
b1000000101010 -
b10 .
b111 2
09
b100000110001000000101010 =
b100 ?
b11 @
b1100 A
b1100 B
b0 D
b101010 E
b1 F
0G
b0 H
1I
0J
b111 K
0L
0M
b1100 N
b0 O
b1000000101010 P
b1000000101010 Q
b1000000101010 R
b100000110001000000101010 W
b11100 X
b100000010101000 Y
b100000011000100 [
b10000011000100000010101000 \
0]
#120000
0!
0#
b11100 %
b100000 &
1:
b11100 ;
b111 <
1>
1S
b100000 X
b100000 Z
b100000011001000 [
#125000
1!
1#
b1000 &
b11111000000000000000001000 '
b1000 (
b0 )
b1000 ,
b1000 -
b0 .
00
b0 2
17
19
b11111000000000000000001000 =
b11111 ?
b0 @
b1000 A
b0 B
b0 D
b1000 E
b1 F
0G
b0 H
0I
0J
b0 K
0L
1M
b0 N
b0 O
b1000 P
b1000 Q
b1000 R
b11111000000000000000001000 W
b1000 X
b100000 Y
b1000000 [
b1111100000000000000000100000 \
1]
#130000
0!
0#
b1000 %
0:
b1000 ;
b10 <
0>
0S
b1000 X
b1100 Z
b101100 [
#135000
1!
1#
b1100 &
b10000110010000000100000 '
b0 (
b1100 )
b1100 *
b1100 +
b10000000100000 ,
b10000000100000 -
b100 .
b1100 /
10
b10 2
07
08
09
b10000110010000000100000 =
b10 ?
b11 @
b0 A
b1100 B
b0 D
b100000 E
b1 F
0G
b0 H
1I
0J
b10 K
0L
0M
b1100 N
b1100 O
b10000000100000 P
b10000000100000 Q
b10000000100000 R
b11 T
b1100 U
b10000110010000000100000 W
b1100 X
b1000000010000000 Y
b1000000010001100 [
b1000011001000000010000000 \
0]
#140000
0!
0#
b1100 %
b10000 &
1:
b1100 ;
b11 <
1>
1S
b10000 X
b10000 Z
b1000000010010000 [
#145000
1!
1#
b0 &
b1000000000000000000000000000 '
b0 )
b0 *
b0 +
b0 ,
b0 -
b0 .
b0 /
00
b0 2
b0 3
17
18
19
b1000000000000000000000000000 =
b0 ?
b0 @
b0 A
b0 B
b10 D
b0 E
b0 F
0G
b0 H
0I
0J
b0 K
0L
1M
b0 N
b0 O
b0 P
b0 Q
b0 R
b0 T
b0 U
b0 W
b0 X
b0 Y
b10000 [
b0 \
0]
#150000
0!
0#
b0 %
0:
b0 ;
b0 <
0>
0S
b0 X
b100 Z
b100 [
#155000
1!
1#
b100 &
b0 '
10
b1 3
07
09
b0 =
b0 ?
b0 @
b0 D
b0 E
b1 F
0G
b0 H
1I
0J
b0 K
0L
0M
b0 P
b0 W
b100 X
0]
#160000
0!
0#
b100 %
b1000 &
1:
b100 ;
b1 <
1>
1S
b1000 X
b1000 Z
b1000 [
#165000
1!
1#
b10100 &
b1100000000000000000000000101 '
b101 ,
b101 -
b11111 .
b1000 /
b10 3
b10 4
17
19
b1100000000000000000000000101 =
b0 ?
b0 @
b11 D
b101 E
b10 F
0G
b10 H
1I
0J
b0 K
0L
1M
b0 N
b101 P
b101 Q
b101 R
b101 W
b10100 X
b10100 Y
b11100 [
b10100 \
0]
#170000
0!
0#
b10100 %
b11000 /
0:
b10100 ;
b101 <
0>
0S
b10100 X
b11000 Z
b101100 [
#175000
1!
1#
b11000 &
b0 '
b0 ,
b0 -
b0 .
b0 /
b1 3
b0 4
07
09
b0 =
b0 ?
b0 @
b0 D
b0 E
b1 F
0G
b0 H
1I
0J
b0 K
0L
0M
b0 N
b0 P
b0 Q
b0 R
b0 W
b11000 X
b0 Y
b11000 [
b0 \
0]
#180000
0!
0#
b11000 %
b11100 &
1:
b11000 ;
b110 <
1>
1S
b11100 X
b11100 Z
b11100 [
#185000
1!
1#
b100000110001000000101010 '
b1100 (
b1100 )
b1000000101010 ,
b1000000101010 -
b10 .
b111 2
19
b100000110001000000101010 =
b100 ?
b11 @
b1100 A
b1100 B
b0 D
b101010 E
b1 F
0G
b0 H
1I
0J
b111 K
0L
0M
b1100 N
b0 O
b1000000101010 P
b1000000101010 Q
b1000000101010 R
b100000110001000000101010 W
b11100 X
b100000010101000 Y
b100000011000100 [
b10000011000100000010101000 \
0]
#190000
0!
0#
b11100 %
b100000 &
0:
b11100 ;
b111 <
0>
0S
b100000 X
b100000 Z
b100000011001000 [
#195000
1!
1#
b1000 &
b11111000000000000000001000 '
b1000 (
b0 )
b1000 ,
b1000 -
b0 .
00
b0 2
17
09
b11111000000000000000001000 =
b11111 ?
b0 @
b1000 A
b0 B
b0 D
b1000 E
b1 F
0G
b0 H
0I
0J
b0 K
0L
1M
b0 N
b0 O
b1000 P
b1000 Q
b1000 R
b11111000000000000000001000 W
b1000 X
b100000 Y
b1000000 [
b1111100000000000000000100000 \
1]
#200000
0!
0#
b1000 %
1:
b1000 ;
b10 <
1>
1S
b1000 X
b1100 Z
b101100 [
#205000
1!
1#
b1100 &
b10000110010000000100000 '
b0 (
b1100 )
b1100 *
b1100 +
b10000000100000 ,
b10000000100000 -
b100 .
b1100 /
10
b10 2
07
08
19
b10000110010000000100000 =
b10 ?
b11 @
b0 A
b1100 B
b0 D
b100000 E
b1 F
0G
b0 H
1I
0J
b10 K
0L
0M
b1100 N
b1100 O
b10000000100000 P
b10000000100000 Q
b10000000100000 R
b11 T
b1100 U
b10000110010000000100000 W
b1100 X
b1000000010000000 Y
b1000000010001100 [
b1000011001000000010000000 \
0]
#210000
0!
0#
b1100 %
b10000 &
0:
b1100 ;
b11 <
0>
0S
b10000 X
b10000 Z
b1000000010010000 [
#215000
1!
1#
b0 &
b1000000000000000000000000000 '
b0 )
b0 *
b0 +
b0 ,
b0 -
b0 .
b0 /
00
b0 2
b0 3
17
18
09
b1000000000000000000000000000 =
b0 ?
b0 @
b0 A
b0 B
b10 D
b0 E
b0 F
0G
b0 H
0I
0J
b0 K
0L
1M
b0 N
b0 O
b0 P
b0 Q
b0 R
b0 T
b0 U
b0 W
b0 X
b0 Y
b10000 [
b0 \
0]
#220000
0!
0#
b0 %
1:
b0 ;
b0 <
1>
1S
b0 X
b100 Z
b100 [
#225000
1!
1#
b100 &
b0 '
10
b1 3
07
19
b0 =
b0 ?
b0 @
b0 D
b0 E
b1 F
0G
b0 H
1I
0J
b0 K
0L
0M
b0 P
b0 W
b100 X
0]
