my_mips.srcs/sources_1/new/pc_calculator.v
module pc_calculator(
    input [31:0] pc,
    input [25:0] jump_addr,
    input [31:0] branch_addr,
    input branch,
    input jump,
    input zero,
    input [31:0] reg_data1,
    output reg [31:0] next_pc
);

    wire [31:0] branch_offset = branch_addr << 2;
    wire [31:0] pc_plus_4 = pc + 32'd4;
    wire [31:0] branch_target = pc_plus_4 + branch_offset;
    wire [31:0] jump_target = {pc_plus_4[31:28], jump_addr, 2'b00};
    
    always @(*) begin
        if (jump) begin
            next_pc = jump_target;
        end
        else if (branch && zero) begin // BEQ
            next_pc = branch_target;
        end
        else if (branch && !zero) begin // BNE
            next_pc = branch_target;
        end
        else if (branch && $signed(reg_data1) < 0) begin // BLTZ
            next_pc = branch_target;
        end
        else if (branch && $signed(reg_data1) >= 0) begin // BGEZ
            next_pc = branch_target;
        end
        else begin
            next_pc = pc_plus_4;
        end
    end
endmodule

my_mips.srcs/sources_1/new/data_memory.v
module data_memory(
    input clk,
    input reset,
    input [5:0] addr,
    input [31:0] write_data,
    input write_en,
    output reg [31:0] read_data
);

    reg [31:0] mem [0:63];
    integer i;
    
    // 初始化数据存储器
    initial begin
        for (i = 0; i < 64; i = i + 1) begin
            mem[i] = i * 4; // 地址值乘以4
        end
    end
    
    always @(negedge clk) begin
        if (reset) begin
            for (i = 0; i < 64; i = i + 1) begin
                mem[i] <= i * 4;
            end
        end
        else if (write_en) begin
            mem[addr] <= write_data;
        end
    end
    
    always @(*) begin
        read_data = mem[addr];
    end
endmodule

my_mips.srcs/sources_1/new/extend.v
module sign_extend(
    input [15:0] in,
    output reg [31:0] out
);

    always @(*) begin
        out = {{16{in[15]}}, in};
    end
endmodule

module zero_extend(
    input [15:0] in,
    output reg [31:0] out
);

    always @(*) begin
        out = {16'b0, in};
    end
endmodule

my_mips.srcs/sources_1/new/alu.v
module alu(
    input [31:0] a,
    input [31:0] b,
    input [3:0] control,
    output reg [31:0] result,
    output zero
);

    assign zero = (result == 32'b0);
    
    always @(*) begin
        case (control)
            4'b0000: result = a & b;    // AND
            4'b0001: result = a | b;    // OR
            4'b0010: result = a + b;    // ADD
            4'b0110: result = a - b;    // SUB
            4'b0111: result = (a < b) ? 32'd1 : 32'd0; // SLT
            4'b1100: result = ~(a | b); // NOR
            default: result = 32'b0;
        endcase
    end
endmodule

my_mips.srcs/sources_1/new/control_unit.v
module control_unit(
    input [5:0] opcode,
    input [5:0] funct,
    output reg [1:0] reg_dst,
    output reg alu_src,
    output reg [1:0] mem_to_reg,
    output reg reg_write,
    output reg mem_write,
    output reg [3:0] alu_control,
    output reg branch,
    output reg jump
);

    always @(*) begin
        case (opcode)
            6'b000000: begin // R-type
                reg_dst = 2'b01;
                alu_src = 1'b0;
                mem_to_reg = 2'b00;
                reg_write = 1'b1;
                mem_write = 1'b0;
                branch = 1'b0;
                jump = 1'b0;
                
                case (funct)
                    6'b100000: alu_control = 4'b0010; // ADD
                    6'b100010: alu_control = 4'b0110; // SUB
                    6'b100100: alu_control = 4'b0000; // AND
                    6'b100101: alu_control = 4'b0001; // OR
                    6'b101010: alu_control = 4'b0111; // SLT
                    6'b001000: begin alu_control = 4'b0000; jump = 1'b1; end // JR
                    default: alu_control = 4'b0000;
                endcase
            end
            
            6'b100011: begin // LW
                reg_dst = 2'b00;
                alu_src = 1'b1;
                mem_to_reg = 2'b01;
                reg_write = 1'b1;
                mem_write = 1'b0;
                alu_control = 4'b0010;
                branch = 1'b0;
                jump = 1'b0;
            end
            
            6'b101011: begin // SW
                reg_dst = 2'b00;
                alu_src = 1'b1;
                mem_to_reg = 2'b00;
                reg_write = 1'b0;
                mem_write = 1'b1;
                alu_control = 4'b0010;
                branch = 1'b0;
                jump = 1'b0;
            end
            
            6'b000100: begin // BEQ
                reg_dst = 2'b00;
                alu_src = 1'b0;
                mem_to_reg = 2'b00;
                reg_write = 1'b0;
                mem_write = 1'b0;
                alu_control = 4'b0110;
                branch = 1'b1;
                jump = 1'b0;
            end
            
            6'b000101: begin // BNE
                reg_dst = 2'b00;
                alu_src = 1'b0;
                mem_to_reg = 2'b00;
                reg_write = 1'b0;
                mem_write = 1'b0;
                alu_control = 4'b0110;
                branch = 1'b1;
                jump = 1'b0;
            end
            
            6'b000010: begin // J
                reg_dst = 2'b00;
                alu_src = 1'b0;
                mem_to_reg = 2'b00;
                reg_write = 1'b0;
                mem_write = 1'b0;
                alu_control = 4'b0000;
                branch = 1'b0;
                jump = 1'b1;
            end
            
            6'b000011: begin // JAL
                reg_dst = 2'b10;
                alu_src = 1'b0;
                mem_to_reg = 2'b10;
                reg_write = 1'b1;
                mem_write = 1'b0;
                alu_control = 4'b0000;
                branch = 1'b0;
                jump = 1'b1;
            end
            
            6'b001000: begin // ADDI
                reg_dst = 2'b00;
                alu_src = 1'b1;
                mem_to_reg = 2'b00;
                reg_write = 1'b1;
                mem_write = 1'b0;
                alu_control = 4'b0010;
                branch = 1'b0;
                jump = 1'b0;
            end
            
            6'b001101: begin // ORI
                reg_dst = 2'b00;
                alu_src = 1'b1;
                mem_to_reg = 2'b00;
                reg_write = 1'b1;
                mem_write = 1'b0;
                alu_control = 4'b0001;
                branch = 1'b0;
                jump = 1'b0;
            end
            
            6'b100000: begin // LB
                reg_dst = 2'b00;
                alu_src = 1'b1;
                mem_to_reg = 2'b01;
                reg_write = 1'b1;
                mem_write = 1'b0;
                alu_control = 4'b0010;
                branch = 1'b0;
                jump = 1'b0;
            end
            
            6'b100100: begin // LBU
                reg_dst = 2'b00;
                alu_src = 1'b1;
                mem_to_reg = 2'b01;
                reg_write = 1'b1;
                mem_write = 1'b0;
                alu_control = 4'b0010;
                branch = 1'b0;
                jump = 1'b0;
            end
            
            6'b100001: begin // LH
                reg_dst = 2'b00;
                alu_src = 1'b1;
                mem_to_reg = 2'b01;
                reg_write = 1'b1;
                mem_write = 1'b0;
                alu_control = 4'b0010;
                branch = 1'b0;
                jump = 1'b0;
            end
            
            6'b100101: begin // LHU
                reg_dst = 2'b00;
                alu_src = 1'b1;
                mem_to_reg = 2'b01;
                reg_write = 1'b1;
                mem_write = 1'b0;
                alu_control = 4'b0010;
                branch = 1'b0;
                jump = 1'b0;
            end
            
            6'b000001: begin // BLTZ/BGEZ
                reg_dst = 2'b00;
                alu_src = 1'b0;
                mem_to_reg = 2'b00;
                reg_write = 1'b0;
                mem_write = 1'b0;
                alu_control = 4'b0111;
                branch = 1'b1;
                jump = 1'b0;
            end
            
            default: begin
                reg_dst = 2'b00;
                alu_src = 1'b0;
                mem_to_reg = 2'b00;
                reg_write = 1'b0;
                mem_write = 1'b0;
                alu_control = 4'b0000;
                branch = 1'b0;
                jump = 1'b0;
            end
        endcase
    end
endmodule

my_mips.srcs/sources_1/new/reg_file.v
module reg_file(
    input clk,
    input reset,
    input [4:0] read_reg1,
    input [4:0] read_reg2,
    input [4:0] write_reg,
    input [31:0] write_data,
    input write_en,
    output reg [31:0] read_data1,
    output reg [31:0] read_data2
);

    reg [31:0] registers [0:31];
    integer i;
    
    // 初始化寄存器文件
    initial begin
        for (i = 0; i < 32; i = i + 1) begin
            registers[i] = i * 4;
        end
    end
    
    always @(negedge clk or posedge reset) begin
        if (reset) begin
            for (i = 0; i < 32; i = i + 1) begin
                registers[i] <= i * 4;
            end
        end
        else if (write_en && write_reg != 0) begin
            registers[write_reg] <= write_data;
        end
    end
    
    always @(*) begin
        read_data1 = (read_reg1 == 0) ? 32'b0 : registers[read_reg1];
        read_data2 = (read_reg2 == 0) ? 32'b0 : registers[read_reg2];
    end
endmodule

my_mips.srcs/sources_1/new/instruction_memory.v
module instruction_memory(
    input clk,
    input [5:0] addr,
    output reg [31:0] instruction
);

    reg [31:0] mem [0:63];
    
    // ³õÊ¼»¯Ö¸Áî´æ´¢Æ÷
    initial begin
        // ²âÊÔ³ÌÐò»úÆ÷Âë
        mem[0] = 32'h00432020; // add $4,$2,$3
        mem[1] = 32'h8c440004; // lw $4,4($2)
        mem[2] = 32'hac450008; // sw $5,8($2)
        mem[3] = 32'h00831022; // sub $2,$4,$3
        mem[4] = 32'h00831025; // or $2,$4,$3
        mem[5] = 32'h00831024; // and $2,$4,$3
        mem[6] = 32'h0083102a; // slt $2,$4,$3
        mem[7] = 32'h10630001; // beq $3,$3,equ (PC+1+1)
        mem[8] = 32'h8c620000; // lw $2,0($3)
        // equ:
        mem[9] = 32'h10640001; // beq $3,$4,exit (PC+1+1)
        mem[10] = 32'hac620000; // sw $2,0($3)
        // exit:
        mem[11] = 32'h08000000; // j main (PC = 0)
        
        // À©Õ¹Ö¸Áî
        mem[12] = 32'h2062000a; // addi $2,$3,10
        mem[13] = 32'h3462000f; // ori $2,$3,0xf
        mem[14] = 32'h80420000; // lb $2,0($2)
        mem[15] = 32'h90420000; // lbu $2,0($2)
        mem[16] = 32'h84420000; // lh $2,0($2)
        mem[17] = 32'h94420000; // lhu $2,0($2)
        mem[18] = 32'h14640001; // bne $3,$4,exit (PC+1+1)
        mem[19] = 32'h04600001; // bltz $3,exit (PC+1+1)
        mem[20] = 32'h04610001; // bgez $3,exit (PC+1+1)
        mem[21] = 32'h0c000000; // jal 0
        mem[22] = 32'h03e00008; // jr $31
    end
    
    always @(posedge clk) begin
        instruction <= mem[addr];
    end
endmodule

my_mips.srcs/sources_1/new/mips_cpu.v
module mips_cpu(
    input clk,
    input reset
);

    // 内部信号定义
    wire [31:0] pc, next_pc, instruction;
    wire [31:0] reg_data1, reg_data2, alu_result, mem_read_data;
    wire [31:0] sign_extend, zero_extend;
    wire [4:0] write_reg;
    wire [31:0] reg_write_data;
    wire reg_write_en, mem_write_en;
    wire [3:0] alu_control;
    wire [1:0] reg_dst, mem_to_reg;
    wire alu_src, branch, jump, zero;
    
    // 时钟边沿控制
    reg clk_rise = 0, clk_fall = 0;  // 添加初始值
    always @(posedge clk) clk_rise <= ~clk_rise;
    always @(negedge clk) clk_fall <= ~clk_fall;
    
    // PC寄存器 (下降沿更新)
    reg [31:0] pc_reg;
    always @(negedge clk or posedge reset) begin
        if (reset) pc_reg <= 32'b0;
        else pc_reg <= next_pc;
    end
    assign pc = pc_reg;
    
    // 指令存储器 (上升沿读取)
    instruction_memory imem(
        .clk(clk_rise),
        .addr(pc[7:2]),
        .instruction(instruction)
    );
    
    // 寄存器文件
    reg_file registers(
        .clk(clk_fall),
        .reset(reset),
        .read_reg1(instruction[25:21]),
        .read_reg2(instruction[20:16]),
        .write_reg(write_reg),
        .write_data(reg_write_data),
        .write_en(reg_write_en),
        .read_data1(reg_data1),
        .read_data2(reg_data2)
    );
    
    // 控制单元
    control_unit control(
        .opcode(instruction[31:26]),
        .funct(instruction[5:0]),
        .reg_dst(reg_dst),
        .alu_src(alu_src),
        .mem_to_reg(mem_to_reg),
        .reg_write(reg_write_en),
        .mem_write(mem_write_en),
        .alu_control(alu_control),
        .branch(branch),
        .jump(jump)
    );
    
    // ALU
    alu main_alu(
        .a(reg_data1),
        .b(alu_src ? sign_extend : reg_data2),
        .control(alu_control),
        .result(alu_result),
        .zero(zero)
    );
    
    // 符号扩展
    sign_extend sign_ext(
        .in(instruction[15:0]),
        .out(sign_extend)
    );
    
    // 零扩展
    zero_extend zero_ext(
        .in(instruction[15:0]),
        .out(zero_extend)
    );
    
    // 数据存储器 (下降沿写入)
    data_memory dmem(
        .clk(clk_fall),
        .reset(reset),
        .addr(alu_result[7:2]),
        .write_data(reg_data2),
        .write_en(mem_write_en),
        .read_data(mem_read_data)
    );
    
    // 下一条PC计算
    pc_calculator pc_calc(
        .pc(pc),
        .jump_addr(instruction[25:0]),
        .branch_addr(sign_extend),
        .branch(branch),
        .jump(jump),
        .zero(zero),
        .reg_data1(reg_data1),
        .next_pc(next_pc)
    );
    
    // 写回寄存器选择
    assign write_reg = (reg_dst == 2'b00) ? instruction[20:16] :
                      (reg_dst == 2'b01) ? instruction[15:11] :
                      5'b11111; // 用于JAL指令
    
    // 写回数据选择
    assign reg_write_data = (mem_to_reg == 2'b00) ? alu_result :
                           (mem_to_reg == 2'b01) ? mem_read_data :
                           (mem_to_reg == 2'b10) ? {pc + 32'd4} :
                           zero_extend; // 用于LUI指令
endmodule

my_mips.srcs/sim_1/new/testbench.v
`timescale 1ns/1ps

module mips_cpu_tb;

    reg clk;
    reg reset;
    integer cycle_count = 0;
    reg [31:0] prev_regs [0:31];
    reg [31:0] prev_mem [0:63];
    
    // 实例化CPU
    mips_cpu cpu(.clk(clk), .reset(reset));
    
    // 时钟生成
    initial begin
        clk = 0;
        forever #5 clk = ~clk;
    end
    
    // 正确的reset处理
    initial begin
        // 初始化所有寄存器和内存的"previous"值
        for (integer i = 0; i < 32; i = i + 1) begin
            prev_regs[i] = 0;
        end
        for (integer i = 0; i < 64; i = i + 1) begin
            prev_mem[i] = 0;
        end
        
        // 应用reset
        reset = 1;
        #20;  // 保持reset一段时间
        reset = 0;
        
        // 运行足够长的时间
        #500;
        $finish;
    end
    
    // R型指令解码辅助函数
    function [64:0] get_r_type_name;
        input [5:0] funct;
        begin
            case (funct)
                6'b100000: get_r_type_name = "ADD";
                6'b100010: get_r_type_name = "SUB";
                6'b100100: get_r_type_name = "AND";
                6'b100101: get_r_type_name = "OR";
                6'b101010: get_r_type_name = "SLT";
                6'b001000: get_r_type_name = "JR";
                default: get_r_type_name = "未知R型";
            endcase
        end
    endfunction
    
    // 监控每个周期的变化
    always @(posedge clk) begin
        if (!reset) begin
            cycle_count = cycle_count + 1;
            
            // 显示当前周期信息
            $display("\n==== 周期 %0d ====", cycle_count);
            $display("PC = %h, 指令 = %h", cpu.pc, cpu.instruction);
            
            // 显示控制信号
            $display("控制信号: opcode=%b, funct=%b", 
                     cpu.instruction[31:26], cpu.instruction[5:0]);
            $display("reg_dst=%b, alu_src=%b, mem_to_reg=%b, reg_write=%b, mem_write=%b", 
                     cpu.control.reg_dst, cpu.control.alu_src, 
                     cpu.control.mem_to_reg, cpu.control.reg_write, 
                     cpu.control.mem_write);
            $display("alu_control=%b, branch=%b, jump=%b",
                     cpu.control.alu_control, cpu.control.branch, 
                     cpu.control.jump);
            
            // 解码指令类型
            case (cpu.instruction[31:26])
                6'b000000: $display("R型指令: %s", get_r_type_name(cpu.instruction[5:0]));
                6'b100011: $display("指令: LW r%0d, %0d(r%0d)", cpu.instruction[20:16], $signed(cpu.instruction[15:0]), cpu.instruction[25:21]);
                6'b101011: $display("指令: SW r%0d, %0d(r%0d)", cpu.instruction[20:16], $signed(cpu.instruction[15:0]), cpu.instruction[25:21]);
                6'b000100: $display("指令: BEQ r%0d, r%0d, %0d", cpu.instruction[25:21], cpu.instruction[20:16], $signed(cpu.instruction[15:0]));
                6'b000101: $display("指令: BNE r%0d, r%0d, %0d", cpu.instruction[25:21], cpu.instruction[20:16], $signed(cpu.instruction[15:0]));
                6'b000010: $display("指令: J %h", {cpu.pc[31:28], cpu.instruction[25:0], 2'b00});
                6'b001000: $display("指令: ADDI r%0d, r%0d, %0d", cpu.instruction[20:16], cpu.instruction[25:21], $signed(cpu.instruction[15:0]));
                6'b001101: $display("指令: ORI r%0d, r%0d, %0d", cpu.instruction[20:16], cpu.instruction[25:21], cpu.instruction[15:0]);
                default: $display("其他指令类型");
            endcase
            
            // 显示寄存器变化
            $display("寄存器变化:");
            for (integer i = 0; i < 32; i = i + 1) begin
                if (prev_regs[i] != cpu.registers.registers[i]) begin
                    $display("  r%0d: %h -> %h", i, prev_regs[i], cpu.registers.registers[i]);
                    prev_regs[i] = cpu.registers.registers[i];
                end
            end
            
            // 显示内存变化
            $display("内存变化:");
            for (integer i = 0; i < 64; i = i + 1) begin
                if (prev_mem[i] != cpu.dmem.mem[i]) begin
                    $display("  mem[%0d]: %h -> %h", i, prev_mem[i], cpu.dmem.mem[i]);
                    prev_mem[i] = cpu.dmem.mem[i];
                end
            end
            
            // ALU结果
            $display("ALU: a=%h, b=%h, result=%h, zero=%b", 
                     cpu.reg_data1, 
                     cpu.alu_src ? cpu.sign_extend : cpu.reg_data2, 
                     cpu.alu_result, 
                     cpu.zero);
            
            $display("Next PC = %h", cpu.next_pc);
        end
    end
endmodule

my_mips.sim/sim_1/behav/xsim/mips_cpu.vcd
$date
   Mon Apr 28 20:09:12 2025
$end
$version
  2018.3
$end
$timescale
  1ps
$end
$scope module mips_cpu_tb $end
$var reg 1 ! clk $end
$var reg 1 " reset $end
$var integer 32 # cycle_count $end
$scope module cpu $end
$var wire 1 $ clk $end
$var wire 1 % reset $end
$var wire 32 & pc [31:0] $end
$var wire 32 ' next_pc [31:0] $end
$var wire 32 ( instruction [31:0] $end
$var wire 32 ) reg_data1 [31:0] $end
$var wire 32 * reg_data2 [31:0] $end
$var wire 32 + alu_result [31:0] $end
$var wire 32 , mem_read_data [31:0] $end
$var wire 32 - sign_extend [31:0] $end
$var wire 32 . zero_extend [31:0] $end
$var wire 5 / write_reg [4:0] $end
$var wire 32 0 reg_write_data [31:0] $end
$var wire 1 1 reg_write_en $end
$var wire 1 2 mem_write_en $end
$var wire 4 3 alu_control [3:0] $end
$var wire 2 4 reg_dst [1:0] $end
$var wire 2 5 mem_to_reg [1:0] $end
$var wire 1 6 alu_src $end
$var wire 1 7 branch $end
$var wire 1 8 jump $end
$var wire 1 9 zero $end
$var reg 1 : clk_rise $end
$var reg 1 ; clk_fall $end
$var reg 32 < pc_reg [31:0] $end
$scope module imem $end
$var wire 1 = clk $end
$var wire 6 > addr [5:0] $end
$var reg 32 ? instruction [31:0] $end
$upscope $end
$scope module registers $end
$var wire 1 @ clk $end
$var wire 1 % reset $end
$var wire 5 A read_reg1 [4:0] $end
$var wire 5 B read_reg2 [4:0] $end
$var wire 5 / write_reg [4:0] $end
$var wire 32 0 write_data [31:0] $end
$var wire 1 1 write_en $end
$var reg 32 C read_data1 [31:0] $end
$var reg 32 D read_data2 [31:0] $end
$var integer 32 E i $end
$upscope $end
$scope module control $end
$var wire 6 F opcode [5:0] $end
$var wire 6 G funct [5:0] $end
$var reg 2 H reg_dst [1:0] $end
$var reg 1 I alu_src $end
$var reg 2 J mem_to_reg [1:0] $end
$var reg 1 K reg_write $end
$var reg 1 L mem_write $end
$var reg 4 M alu_control [3:0] $end
$var reg 1 N branch $end
$var reg 1 O jump $end
$upscope $end
$scope module main_alu $end
$var wire 32 ) a [31:0] $end
$var wire 32 P b [31:0] $end
$var wire 4 3 control [3:0] $end
$var reg 32 Q result [31:0] $end
$var wire 1 9 zero $end
$upscope $end
$scope module sign_ext $end
$var wire 16 R in [15:0] $end
$var reg 32 S out [31:0] $end
$upscope $end
$scope module zero_ext $end
$var wire 16 R in [15:0] $end
$var reg 32 T out [31:0] $end
$upscope $end
$scope module dmem $end
$var wire 1 U clk $end
$var wire 1 % reset $end
$var wire 6 V addr [5:0] $end
$var wire 32 * write_data [31:0] $end
$var wire 1 2 write_en $end
$var reg 32 W read_data [31:0] $end
$var integer 32 X i $end
$upscope $end
$scope module pc_calc $end
$var wire 32 & pc [31:0] $end
$var wire 26 Y jump_addr [25:0] $end
$var wire 32 - branch_addr [31:0] $end
$var wire 1 7 branch $end
$var wire 1 8 jump $end
$var wire 1 9 zero $end
$var wire 32 ) reg_data1 [31:0] $end
$var reg 32 Z next_pc [31:0] $end
$var wire 32 [ branch_offset [31:0] $end
$var wire 32 \ pc_plus_4 [31:0] $end
$var wire 32 ] branch_target [31:0] $end
$var wire 32 ^ jump_target [31:0] $end
$upscope $end
$upscope $end
$scope begin Block44_18 $end
$var integer 32 _ i $end
$upscope $end
$scope begin Block53_19 $end
$var integer 32 ` i $end
$upscope $end
$scope begin Block90_21 $end
$var integer 32 a i $end
$upscope $end
$scope begin Block94_22 $end
$var integer 32 b i $end
$upscope $end
$scope begin Block110_24 $end
$var integer 32 c i $end
$upscope $end
$scope begin Block116_25 $end
$var integer 32 d i $end
$upscope $end
$scope function get_r_type_name $end
$var reg 65 e get_r_type_name [64:0] $end
$var reg 6 f funct [5:0] $end
$upscope $end
$upscope $end
$enddefinitions $end
#0
$dumpvars
0!
1"
b0 #
0$
1%
b0 &
b100 '
bx (
bx )
bx *
bx +
bx ,
bx -
bx .
bx /
bx 0
x1
x2
bx 3
bx 4
bx 5
x6
x7
x8
x9
x:
x;
b0 <
x=
b0 >
bx ?
x@
bx A
bx B
bx C
bx D
b100000 E
bx F
bx G
bx H
xI
bx J
xK
xL
bx M
xN
xO
bx P
bx Q
bx R
bx S
bx T
xU
bx V
bx W
b1000000 X
bx Y
b100 Z
bx00 [
b100 \
bx ]
b0xxxxxxxxxxxxxxxxxxxxxxxxxx00 ^
bx _
bx `
b100000 a
b1000000 b
bx c
bx d
bx e
bx f
$end
#5000
1!
1$
#10000
0!
0"
0$
0%
b100 &
b1000 '
b100 <
b1 >
b1000 Z
b1000 \
bx ]
#15000
1!
b1 #
1$
b100000 _
b1000000 `
#20000
0!
0$
b1000 &
b1100 '
b1000 <
b10 >
b1100 Z
b1100 \
bx ]
#25000
1!
b10 #
1$
b100000 _
b1000000 `
#30000
0!
0$
b1100 &
b10000 '
b1100 <
b11 >
b10000 Z
b10000 \
bx ]
#35000
1!
b11 #
1$
b100000 _
b1000000 `
#40000
0!
0$
b10000 &
b10100 '
b10000 <
b100 >
b10100 Z
b10100 \
bx ]
#45000
1!
b100 #
1$
b100000 _
b1000000 `
#50000
0!
0$
b10100 &
b11000 '
b10100 <
b101 >
b11000 Z
b11000 \
bx ]
#55000
1!
b101 #
1$
b100000 _
b1000000 `
#60000
0!
0$
b11000 &
b11100 '
b11000 <
b110 >
b11100 Z
b11100 \
bx ]
#65000
1!
b110 #
1$
b100000 _
b1000000 `
#70000
0!
0$
b11100 &
b100000 '
b11100 <
b111 >
b100000 Z
b100000 \
bx ]
#75000
1!
b111 #
1$
b100000 _
b1000000 `
#80000
0!
0$
b100000 &
b100100 '
b100000 <
b1000 >
b100100 Z
b100100 \
bx ]
#85000
1!
b1000 #
1$
b100000 _
b1000000 `
#90000
0!
0$
b100100 &
b101000 '
b100100 <
b1001 >
b101000 Z
b101000 \
bx ]
#95000
1!
b1001 #
1$
b100000 _
b1000000 `
#100000
0!
0$
b101000 &
b101100 '
b101000 <
b1010 >
b101100 Z
b101100 \
bx ]
#105000
1!
b1010 #
1$
b100000 _
b1000000 `
#110000
0!
0$
b101100 &
b110000 '
b101100 <
b1011 >
b110000 Z
b110000 \
bx ]
#115000
1!
b1011 #
1$
b100000 _
b1000000 `
#120000
0!
0$
b110000 &
b110100 '
b110000 <
b1100 >
b110100 Z
b110100 \
bx ]
#125000
1!
b1100 #
1$
b100000 _
b1000000 `
#130000
0!
0$
b110100 &
b111000 '
b110100 <
b1101 >
b111000 Z
b111000 \
bx ]
#135000
1!
b1101 #
1$
b100000 _
b1000000 `
#140000
0!
0$
b111000 &
b111100 '
b111000 <
b1110 >
b111100 Z
b111100 \
bx ]
#145000
1!
b1110 #
1$
b100000 _
b1000000 `
#150000
0!
0$
b111100 &
b1000000 '
b111100 <
b1111 >
b1000000 Z
b1000000 \
bx ]
#155000
1!
b1111 #
1$
b100000 _
b1000000 `
#160000
0!
0$
b1000000 &
b1000100 '
b1000000 <
b10000 >
b1000100 Z
b1000100 \
bx ]
#165000
1!
b10000 #
1$
b100000 _
b1000000 `
#170000
0!
0$
b1000100 &
b1001000 '
b1000100 <
b10001 >
b1001000 Z
b1001000 \
bx ]
#175000
1!
b10001 #
1$
b100000 _
b1000000 `
#180000
0!
0$
b1001000 &
b1001100 '
b1001000 <
b10010 >
b1001100 Z
b1001100 \
bx ]
#185000
1!
b10010 #
1$
b100000 _
b1000000 `
#190000
0!
0$
b1001100 &
b1010000 '
b1001100 <
b10011 >
b1010000 Z
b1010000 \
bx ]
#195000
1!
b10011 #
1$
b100000 _
b1000000 `
#200000
0!
0$
b1010000 &
b1010100 '
b1010000 <
b10100 >
b1010100 Z
b1010100 \
bx ]
#205000
1!
b10100 #
1$
b100000 _
b1000000 `
#210000
0!
0$
b1010100 &
b1011000 '
b1010100 <
b10101 >
b1011000 Z
b1011000 \
bx ]
#215000
1!
b10101 #
1$
b100000 _
b1000000 `
#220000
0!
0$
b1011000 &
b1011100 '
b1011000 <
b10110 >
b1011100 Z
b1011100 \
bx ]
#225000
1!
b10110 #
1$
b100000 _
b1000000 `
#230000
0!
0$
b1011100 &
b1100000 '
b1011100 <
b10111 >
b1100000 Z
b1100000 \
bx ]
#235000
1!
b10111 #
1$
b100000 _
b1000000 `
#240000
0!
0$
b1100000 &
b1100100 '
b1100000 <
b11000 >
b1100100 Z
b1100100 \
bx ]
#245000
1!
b11000 #
1$
b100000 _
b1000000 `
#250000
0!
0$
b1100100 &
b1101000 '
b1100100 <
b11001 >
b1101000 Z
b1101000 \
bx ]
#255000
1!
b11001 #
1$
b100000 _
b1000000 `
#260000
0!
0$
b1101000 &
b1101100 '
b1101000 <
b11010 >
b1101100 Z
b1101100 \
bx ]
#265000
1!
b11010 #
1$
b100000 _
b1000000 `
#270000
0!
0$
b1101100 &
b1110000 '
b1101100 <
b11011 >
b1110000 Z
b1110000 \
bx ]
#275000
1!
b11011 #
1$
b100000 _
b1000000 `
#280000
0!
0$
b1110000 &
b1110100 '
b1110000 <
b11100 >
b1110100 Z
b1110100 \
bx ]
#285000
1!
b11100 #
1$
b100000 _
b1000000 `
#290000
0!
0$
b1110100 &
b1111000 '
b1110100 <
b11101 >
b1111000 Z
b1111000 \
bx ]
#295000
1!
b11101 #
1$
b100000 _
b1000000 `
#300000
0!
0$
b1111000 &
b1111100 '
b1111000 <
b11110 >
b1111100 Z
b1111100 \
bx ]
#305000
1!
b11110 #
1$
b100000 _
b1000000 `
#310000
0!
0$
b1111100 &
b10000000 '
b1111100 <
b11111 >
b10000000 Z
b10000000 \
bx ]
#315000
1!
b11111 #
1$
b100000 _
b1000000 `
#320000
0!
0$
b10000000 &
b10000100 '
b10000000 <
b100000 >
b10000100 Z
b10000100 \
bx ]
#325000
1!
b100000 #
1$
b100000 _
b1000000 `
#330000
0!
0$
b10000100 &
b10001000 '
b10000100 <
b100001 >
b10001000 Z
b10001000 \
bx ]
#335000
1!
b100001 #
1$
b100000 _
b1000000 `
#340000
0!
0$
b10001000 &
b10001100 '
b10001000 <
b100010 >
b10001100 Z
b10001100 \
bx ]
#345000
1!
b100010 #
1$
b100000 _
b1000000 `
#350000
0!
0$
b10001100 &
b10010000 '
b10001100 <
b100011 >
b10010000 Z
b10010000 \
bx ]
#355000
1!
b100011 #
1$
b100000 _
b1000000 `
#360000
0!
0$
b10010000 &
b10010100 '
b10010000 <
b100100 >
b10010100 Z
b10010100 \
bx ]
#365000
1!
b100100 #
1$
b100000 _
b1000000 `
#370000
0!
0$
b10010100 &
b10011000 '
b10010100 <
b100101 >
b10011000 Z
b10011000 \
bx ]
#375000
1!
b100101 #
1$
b100000 _
b1000000 `
#380000
0!
0$
b10011000 &
b10011100 '
b10011000 <
b100110 >
b10011100 Z
b10011100 \
bx ]
#385000
1!
b100110 #
1$
b100000 _
b1000000 `
#390000
0!
0$
b10011100 &
b10100000 '
b10011100 <
b100111 >
b10100000 Z
b10100000 \
bx ]
#395000
1!
b100111 #
1$
b100000 _
b1000000 `
#400000
0!
0$
b10100000 &
b10100100 '
b10100000 <
b101000 >
b10100100 Z
b10100100 \
bx ]
#405000
1!
b101000 #
1$
b100000 _
b1000000 `
#410000
0!
0$
b10100100 &
b10101000 '
b10100100 <
b101001 >
b10101000 Z
b10101000 \
bx ]
#415000
1!
b101001 #
1$
b100000 _
b1000000 `
#420000
0!
0$
b10101000 &
b10101100 '
b10101000 <
b101010 >
b10101100 Z
b10101100 \
bx ]
#425000
1!
b101010 #
1$
b100000 _
b1000000 `
#430000
0!
0$
b10101100 &
b10110000 '
b10101100 <
b101011 >
b10110000 Z
b10110000 \
bx ]
#435000
1!
b101011 #
1$
b100000 _
b1000000 `
#440000
0!
0$
b10110000 &
b10110100 '
b10110000 <
b101100 >
b10110100 Z
b10110100 \
bx ]
#445000
1!
b101100 #
1$
b100000 _
b1000000 `
#450000
0!
0$
b10110100 &
b10111000 '
b10110100 <
b101101 >
b10111000 Z
b10111000 \
bx ]
#455000
1!
b101101 #
1$
b100000 _
b1000000 `
#460000
0!
0$
b10111000 &
b10111100 '
b10111000 <
b101110 >
b10111100 Z
b10111100 \
bx ]
#465000
1!
b101110 #
1$
b100000 _
b1000000 `
#470000
0!
0$
b10111100 &
b11000000 '
b10111100 <
b101111 >
b11000000 Z
b11000000 \
bx ]
#475000
1!
b101111 #
1$
b100000 _
b1000000 `
#480000
0!
0$
b11000000 &
b11000100 '
b11000000 <
b110000 >
b11000100 Z
b11000100 \
bx ]
#485000
1!
b110000 #
1$
b100000 _
b1000000 `
#490000
0!
0$
b11000100 &
b11001000 '
b11000100 <
b110001 >
b11001000 Z
b11001000 \
bx ]
#495000
1!
b110001 #
1$
b100000 _
b1000000 `
#500000
0!
0$
b11001000 &
b11001100 '
b11001000 <
b110010 >
b11001100 Z
b11001100 \
bx ]
#505000
1!
b110010 #
1$
b100000 _
b1000000 `
#510000
b100000 c
b10000 d
